ibslib/__init__.py
ibslib/struct_dict.py
ibslib/structure.py
ibslib/analysis/__init__.py
ibslib/analysis/dictops.py
ibslib/calculators/__init__.py
ibslib/calculators/aims.py
ibslib/calculators/k_grid_fn.py
ibslib/calculators/mbd.py
ibslib/calculators/slurm.py
ibslib/calculators/slurm_arguments.py
ibslib/io/__init__.py
ibslib/io/aims_extractor.py
ibslib/io/check.py
ibslib/io/energy_hierarchy.py
ibslib/io/extract.py
ibslib/io/hab_extractor.py
ibslib/io/mbd.py
ibslib/io/read.py
ibslib/io/write.py
ibslib/structures/__init__.py
ibslib/structures/utils.py
ocelot_ogre-0.1.dist-info/licenses/LICENSE
ogre/__init__.py
ogre/generators.py
ogre/utils/__init__.py
ogre/utils/surface_energy.py
ogre/utils/unique_planes.py
ogre/utils/utils.py
ogre/utils/wulffmaker.py
ocelot_ogre-0.1.dist-info/METADATA
ocelot_ogre-0.1.dist-info/WHEEL
ocelot_ogre-0.1.dist-info/top_level.txt
ocelot_ogre-0.1.dist-info/RECORD
